gen_trace/__init__.py
gen_trace/__main__.py
gen_trace/c_euclidean.py
gen_trace/cmat2aset.pyc
gen_trace/cmat2tset.py
gen_trace/gen_aset.py
gen_trace/gen_chunksize.py
gen_trace/gen_cset.py
gen_trace/gen_mask.pyc
gen_trace/gen_slopes.py
gen_trace/gen_trace.pyc
gen_trace/gen_tset.py
gen_trace/get_angle.py
gen_trace/get_slope.py
gen_trace/label_tset.py
gen_trace/plot_pset.py
gen_trace/remove_indices.py
gen_trace/topn_sorted.py
gen_trace/tset2pset.py
LICENSE
gen_trace-0.1.0.dist-info/entry_points.txt
gen_trace-0.1.0.dist-info/LICENSE
gen_trace-0.1.0.dist-info/WHEEL
gen_trace-0.1.0.dist-info/METADATA
gen_trace-0.1.0.dist-info/RECORD
